sqlinclause/__init__.py
sqlinclause/in_var_extractor.py
sqlinclause/main.py
sqlinclause/placeholder_extractor.py
sqlinclause-0.0.1.dist-info/DESCRIPTION.rst
sqlinclause-0.0.1.dist-info/METADATA
sqlinclause-0.0.1.dist-info/RECORD
sqlinclause-0.0.1.dist-info/WHEEL
sqlinclause-0.0.1.dist-info/metadata.json
sqlinclause-0.0.1.dist-info/top_level.txt
test/__init__.py
test/test.py
