Metadata-Version: 2.0
Name: sqlinclause
Version: 0.0.1
Summary: SQL utility to write variable length IN-clause.
Home-page: UNKNOWN
Author: Miura Takuma
Author-email: takuma-miura@m3.com
License: MIT
Keywords: SQL IN
Platform: UNKNOWN
Requires-Dist: sqlparse
